{
    "my_timestamp": 1744281357.1334321,
    "my_local_time": "2025-04-10 07:35:57",
    "positions": [
        {
            "ticket": 142515634,
            "symbol": "USDJPY",
            "type": "SELL",
            "volume": 0.01,
            "price_open": 145.864,
            "sl": 145.72,
            "tp": 137.111,
            "price_current": 145.637,
            "profit": 1.56,
            "swap": 0.0,
            "magic": 920609,
            "time_open": "2025-04-10 13:16:47",
            "time_raw": 1744291007,
            "comment": "Python Auto Trad"
        },
        {
            "ticket": 142516516,
            "symbol": "USDCHF",
            "type": "SELL",
            "volume": 0.01,
            "price_open": 0.8417,
            "sl": 0.84102,
            "tp": 0.7912,
            "price_current": 0.84054,
            "profit": 1.38,
            "swap": 0.0,
            "magic": 697365,
            "time_open": "2025-04-10 13:19:57",
            "time_raw": 1744291197,
            "comment": "Python Auto Trad"
        },
        {
            "ticket": 142516787,
            "symbol": "USDJPY",
            "type": "SELL",
            "volume": 0.01,
            "price_open": 145.853,
            "sl": 145.72,
            "tp": 137.103,
            "price_current": 145.637,
            "profit": 1.48,
            "swap": 0.0,
            "magic": 825354,
            "time_open": "2025-04-10 13:20:59",
            "time_raw": 1744291259,
            "comment": "Python Auto Trad"
        },
        {
            "ticket": 142519241,
            "symbol": "USDCHF",
            "type": "SELL",
            "volume": 0.01,
            "price_open": 0.84098,
            "sl": 0.84095,
            "tp": 0.7905,
            "price_current": 0.84054,
            "profit": 0.52,
            "swap": 0.0,
            "magic": 679775,
            "time_open": "2025-04-10 13:28:16",
            "time_raw": 1744291696,
            "comment": "Python Auto Trad"
        },
        {
            "ticket": 142519485,
            "symbol": "USDJPY",
            "type": "SELL",
            "volume": 0.01,
            "price_open": 145.731,
            "sl": 145.72,
            "tp": 136.989,
            "price_current": 145.637,
            "profit": 0.65,
            "swap": 0.0,
            "magic": 635401,
            "time_open": "2025-04-10 13:29:33",
            "time_raw": 1744291773,
            "comment": "Python Auto Trad"
        },
        {
            "ticket": 142520243,
            "symbol": "USDJPY",
            "type": "SELL",
            "volume": 0.01,
            "price_open": 145.759,
            "sl": 145.72,
            "tp": 137.013,
            "price_current": 145.637,
            "profit": 0.84,
            "swap": 0.0,
            "magic": 814714,
            "time_open": "2025-04-10 13:31:35",
            "time_raw": 1744291895,
            "comment": "Python Auto Trad"
        },
        {
            "ticket": 142520377,
            "symbol": "GBPUSD",
            "type": "BUY",
            "volume": 0.01,
            "price_open": 1.2916,
            "sl": 1.2906,
            "tp": 1.36909,
            "price_current": 1.29123,
            "profit": -0.37,
            "swap": 0.0,
            "magic": 488098,
            "time_open": "2025-04-10 13:32:12",
            "time_raw": 1744291932,
            "comment": "Python Auto Trad"
        },
        {
            "ticket": 142520597,
            "symbol": "USDJPY",
            "type": "SELL",
            "volume": 0.01,
            "price_open": 145.721,
            "sl": 145.716,
            "tp": 136.978,
            "price_current": 145.637,
            "profit": 0.58,
            "swap": 0.0,
            "magic": 972362,
            "time_open": "2025-04-10 13:33:53",
            "time_raw": 1744292033,
            "comment": "Python Auto Trad"
        },
        {
            "ticket": 142520807,
            "symbol": "USDCHF",
            "type": "SELL",
            "volume": 0.01,
            "price_open": 0.84067,
            "sl": 0.84102,
            "tp": 0.79024,
            "price_current": 0.84054,
            "profit": 0.15,
            "swap": 0.0,
            "magic": 761037,
            "time_open": "2025-04-10 13:35:05",
            "time_raw": 1744292105,
            "comment": "Python Auto Trad"
        }
    ]
}